{
    "page": {
      "title": "弗劳恩科技 - 公司简介"
    },
    "hero": {
      "title": "公司简介"
    },
    "company": {
      "title": "弗劳恩科技",
      "p1": "弗劳恩科技，2005年起步，作为粤港澳大湾区领先的科研综合服务与创新孵化平台，始终专注于为高等院校、科研院所及医疗机构提供全链条科研赋能解决方案。弗劳恩科技创始团队源自大型国企，兼具市场化运营能力与科研资源整合优势，公司以前瞻性视野聚焦“基础研究—技术研发—成果转化”三大核心环节，助力科研生态的升级与产业创新。弗劳恩科技依托近30年的行业深耕构建科研服务生态，打造了覆盖实验设备、技术咨询、课题协作、数据管理及产业孵化的完整服务体系，累计服务100+家科研机构，在深圳科研服务细分市场占有率稳居首位，成为领域内标杆企业。",
      "p2": "弗劳恩科技创新孵化加速引擎，通过战略投资布局生物技术引进、生物医药、医学影像、政府与产业咨询等高技术领域，成功孵化科研设施技术引进服务平台、SCANCO Micro CT 中国服务中心、血清与生长因子定制中心、政府采购招投标云平台、政府与产业咨询服务等多个产业化项目，推动创新成果与技术实现商业转化，形成“科研服务—项目孵化—产业落地”的良性循环。目前已构建起产学研协同创新平台，覆盖大湾区 20+ 重点实验室协同网络，为政府及行业输送联合研究成果。",
      "values": {
        "label": "企业价值观：",
        "text": "诚信靠谱，客户为主，卓越超群，合作共赢"
      },
      "principles": {
        "label": "企业服务宗旨：",
        "text": "专业深耕、服务创新、诚信为本、持续赋能"
      },
      "vision": {
        "label": "企业愿景：",
        "text": "打造一流的区域性科研赋能平台"
      },
      "mission": {
        "label": "企业使命：",
        "text": "让科研更有效率，让创新更有价值"
      }
    },
    "timeline": {
      "title": "公司发展历程",
      "subtitle": "创新驱动的发展之路",
      "items": [
        { "year": "2005年前", "desc": "从事政府采购对外贸易基础性外包业务" },
        { "year": "2006年",   "desc": "初步构建新型政府采购供应链服务平台" },
        { "year": "2011年",   "desc": "科研领域政府供应链服务平台搭建，聚焦专业院校、科研院所、医疗机构三大领域" },
        { "year": "2015年",   "desc": "科研领域政府供应链服务平台走向成熟" },
        { "year": "2016年",   "desc": "开启服务性陪跑式投资之路" },
        { "year": "2017年",   "desc": "自主开发政府采购全流程电子化技术及落地方案，成功孵化若干中小招标代理机构" },
        { "year": "2018年",   "desc": "深圳海关首家胎牛血清进口企业；截至2025年，累计服务200+实验室，是大湾区最大血清进口单位。" },
        { "year": "2018年",   "desc": "弗劳恩咨询业务启航，构建“政策研究+产业规划+定制策划”服务体系；独创 G2B 模型，深度参与大湾区 20+ 重点项目。" },
        { "year": "2018年",   "desc": "Scanco MicroCT 中国深圳扫描服务中心成立" },
        { "year": "2019年",   "desc": "合作超过100家高校、医疗机构、研究院所，成为科研领域供应链服务平台行业标杆" },
        { "year": "2021年",   "desc": "科技服务&投资平台迈向成长期，综合扫描检测、生物耗材、新药研发技术引进、干细胞转化等板块" },
        { "year": "2024年",   "desc": "2024年5月荣获“AEO”高级认证企业证书" },
        { "year": "2024年",   "desc": "深圳高校合作覆盖率 95%+，业务延伸至广州、佛山、江门等大湾区核心城市" }
      ]
    },
    "nav": {
      "home": "首页",
      "government": "公共采购服务",
      "biomed": "生物医学研究服务",
      "biomed_consumables": "生物耗材",
      "biomed_scanning": "扫描检测",
      "academy": "采购通学院",
      "about": "关于我们",
      "intro": "公司简介",
      "customers": "服务客户",
      "contact": "联系我们"
    }
  }
  